{
 "completions": [
  {
   "id": 188,
   "lead_time": 20,
   "result": [
    {
     "from_name": "ner",
     "honeypot": true,
     "id": "c4c9bb193b294876a1ed3e1bc245da9d",
     "source": "$text",
     "to_name": "text",
     "type": "labels",
     "value": {
      "start": 0,
      "end": 33,
      "labels": [
       "PERSON"
      ],
      "text": "KARTIK GOYAL kartikg479@gmail.com"
     }
    },
    {
     "from_name": "ner",
     "honeypot": true,
     "id": "8b2f80caf17940a69f4cb44964f4eede",
     "source": "$text",
     "to_name": "text",
     "type": "labels",
     "value": {
      "start": 34,
      "end": 44,
      "labels": [
       "Phone"
      ],
      "text": "9818865265"
     }
    },
    {
     "from_name": "ner",
     "honeypot": true,
     "id": "4ab16ef69837421284c52d23b0b633e2",
     "source": "$text",
     "to_name": "text",
     "type": "labels",
     "value": {
      "start": 371,
      "end": 377,
      "labels": [
       "EducationDegree"
      ],
      "text": "BJ(MC)"
     }
    },
    {
     "from_name": "ner",
     "honeypot": true,
     "id": "5efde3b2bf0d47789964b841c280b75d",
     "source": "$text",
     "to_name": "text",
     "type": "labels",
     "value": {
      "start": 378,
      "end": 391,
      "labels": [
       "ORG"
      ],
      "text": "IP UNIVERSITY"
     }
    },
    {
     "from_name": "ner",
     "honeypot": true,
     "id": "3130cf678a304574ae7fb821195c3b4d",
     "source": "$text",
     "to_name": "text",
     "type": "labels",
     "value": {
      "start": 394,
      "end": 405,
      "labels": [
       "PERSON"
      ],
      "text": "Kasturi Ram"
     }
    },
    {
     "from_name": "ner",
     "honeypot": true,
     "id": "27f724ffc7fc4330adc00474bb585f3a",
     "source": "$text",
     "to_name": "text",
     "type": "labels",
     "value": {
      "start": 406,
      "end": 433,
      "labels": [
       "ORG"
      ],
      "text": "College of Higher Education"
     }
    },
    {
     "from_name": "ner",
     "honeypot": true,
     "id": "ebc80f9b139a4d009589e0e4af499b70",
     "source": "$text",
     "to_name": "text",
     "type": "labels",
     "value": {
      "start": 434,
      "end": 437,
      "labels": [
       "CARDINAL"
      ],
      "text": "78%"
     }
    },
    {
     "from_name": "ner",
     "honeypot": true,
     "id": "eaaab4eb4b69490e9ceaa206a1d82fd2",
     "source": "$text",
     "to_name": "text",
     "type": "labels",
     "value": {
      "start": 438,
      "end": 447,
      "labels": [
       "DATE"
      ],
      "text": "2015-2018"
     }
    },
    {
     "from_name": "ner",
     "honeypot": true,
     "id": "342918a5fe10401984f597908cecd2d5",
     "source": "$text",
     "to_name": "text",
     "type": "labels",
     "value": {
      "start": 434,
      "end": 437,
      "labels": [
       "CARDINAL"
      ],
      "text": "78%"
     }
    },
    {
     "from_name": "ner",
     "honeypot": true,
     "id": "fc77202ae9a2454b9f6f1b980b30b8a8",
     "source": "$text",
     "to_name": "text",
     "type": "labels",
     "value": {
      "start": 492,
      "end": 495,
      "labels": [
       "CARDINAL"
      ],
      "text": "59%"
     }
    },
    {
     "from_name": "ner",
     "honeypot": true,
     "id": "4875989452da4ad6bfda1516804810ad",
     "source": "$text",
     "to_name": "text",
     "type": "labels",
     "value": {
      "start": 595,
      "end": 626,
      "labels": [
       "ORG"
      ],
      "text": "K.R MANGALAM UNIVERSITY, Sohna,"
     }
    },
    {
     "from_name": "ner",
     "honeypot": true,
     "id": "c16b8ceb784d49dcb597e13226241675",
     "source": "$text",
     "to_name": "text",
     "type": "labels",
     "value": {
      "start": 627,
      "end": 635,
      "labels": [
       "GPE"
      ],
      "text": "Gurugram"
     }
    },
    {
     "from_name": "ner",
     "honeypot": true,
     "id": "beedf2f7dd9a478cb8c7ee5c082551f7",
     "source": "$text",
     "to_name": "text",
     "type": "labels",
     "value": {
      "start": 661,
      "end": 675,
      "labels": [
       "DATE"
      ],
      "text": "September 2018"
     }
    },
    {
     "from_name": "ner",
     "honeypot": true,
     "id": "dd81ed4587ba46dcb4e48d8476268dfb",
     "source": "$text",
     "to_name": "text",
     "type": "labels",
     "value": {
      "start": 764,
      "end": 767,
      "labels": [
       "DATE"
      ],
      "text": "One"
     }
    },
    {
     "from_name": "ner",
     "honeypot": true,
     "id": "1e45266724e64dcbb3513572a7143e9d",
     "source": "$text",
     "to_name": "text",
     "type": "labels",
     "value": {
      "start": 768,
      "end": 773,
      "labels": [
       "ExperianceYears"
      ],
      "text": "Month"
     }
    },
    {
     "from_name": "ner",
     "honeypot": true,
     "id": "9930e8987ec548e99f19301647838031",
     "source": "$text",
     "to_name": "text",
     "type": "labels",
     "value": {
      "start": 774,
      "end": 784,
      "labels": [
       "Designation"
      ],
      "text": "Internship"
     }
    },
    {
     "from_name": "ner",
     "honeypot": true,
     "id": "63ee8c363158466098324387bb90782a",
     "source": "$text",
     "to_name": "text",
     "type": "labels",
     "value": {
      "start": 788,
      "end": 803,
      "labels": [
       "ORG"
      ],
      "text": "History Channel"
     }
    },
    {
     "from_name": "ner",
     "honeypot": true,
     "id": "4e5d0f604ae9405498406c84332112ff",
     "source": "$text",
     "to_name": "text",
     "type": "labels",
     "value": {
      "start": 810,
      "end": 833,
      "labels": [
       "DATE"
      ],
      "text": "July- 10th August 2017)"
     }
    },
    {
     "from_name": "ner",
     "honeypot": true,
     "id": "71e59c9986394295918b2df7cbdf3404",
     "source": "$text",
     "to_name": "text",
     "type": "labels",
     "value": {
      "start": 1980,
      "end": 1996,
      "labels": [
       "DOB"
      ],
      "text": "26 December 1996"
     }
    },
    {
     "from_name": "ner",
     "honeypot": true,
     "id": "de0607e3dc614e89ac7d9e8bddb12300",
     "source": "$text",
     "to_name": "text",
     "type": "labels",
     "value": {
      "start": 2148,
      "end": 2158,
      "labels": [
       "PERSON"
      ],
      "text": "Kiran Bala"
     }
    },
    {
     "from_name": "ner",
     "honeypot": true,
     "id": "02ed3fc360a0440aaba8ed84e9e64ff5",
     "source": "$text",
     "to_name": "text",
     "type": "labels",
     "value": {
      "start": 2188,
      "end": 2232,
      "labels": [
       "ORG"
      ],
      "text": "Mass Communication K.R. Mangalam University,"
     }
    },
    {
     "from_name": "ner",
     "honeypot": true,
     "id": "cc462dae575d4ed09ed6fae10fe41f22",
     "source": "$text",
     "to_name": "text",
     "type": "labels",
     "value": {
      "start": 627,
      "end": 635,
      "labels": [
       "GPE"
      ],
      "text": "Gurugram"
     }
    },
    {
     "from_name": "ner",
     "honeypot": true,
     "id": "43ba02110e1847c2b912be10ff4e6bc5",
     "source": "$text",
     "to_name": "text",
     "type": "labels",
     "value": {
      "start": 2253,
      "end": 2263,
      "labels": [
       "Phone"
      ],
      "text": "9711909988"
     }
    },
    {
     "from_name": "ner",
     "honeypot": true,
     "id": "34ffa12bfce0489b80ed8443e6c4ea62",
     "source": "$text",
     "to_name": "text",
     "type": "labels",
     "value": {
      "start": 2274,
      "end": 2298,
      "labels": [
       "Email"
      ],
      "text": "kiranbkhanna75@gmail.com"
     }
    },
    {
     "from_name": "ner",
     "honeypot": true,
     "id": "d6a72a71a9304aa5a02993be644d503a",
     "source": "$text",
     "to_name": "text",
     "type": "labels",
     "value": {
      "start": 2303,
      "end": 2321,
      "labels": [
       "PERSON"
      ],
      "text": "Manasvi Maheshwari"
     }
    },
    {
     "from_name": "ner",
     "honeypot": true,
     "id": "8426c8bda65b414e99c52be45e3eeca1",
     "source": "$text",
     "to_name": "text",
     "type": "labels",
     "value": {
      "start": 2322,
      "end": 2341,
      "labels": [
       "Designation"
      ],
      "text": "Assistant Professor"
     }
    },
    {
     "from_name": "ner",
     "honeypot": true,
     "id": "5cddcd8454ca4b0eb375c64443d7f312",
     "source": "$text",
     "to_name": "text",
     "type": "labels",
     "value": {
      "start": 2207,
      "end": 2232,
      "labels": [
       "ORG"
      ],
      "text": "K.R. Mangalam University,"
     }
    },
    {
     "from_name": "ner",
     "honeypot": true,
     "id": "89f8ace0fa5d48fc88af55896b0f9973",
     "source": "$text",
     "to_name": "text",
     "type": "labels",
     "value": {
      "start": 620,
      "end": 635,
      "labels": [
       "GPE"
      ],
      "text": "Sohna, Gurugram"
     }
    },
    {
     "from_name": "ner",
     "honeypot": true,
     "id": "28250fcb89b34e629d804ec149bfecc1",
     "source": "$text",
     "to_name": "text",
     "type": "labels",
     "value": {
      "start": 2430,
      "end": 2440,
      "labels": [
       "Phone"
      ],
      "text": "9999311086"
     }
    },
    {
     "from_name": "ner",
     "honeypot": true,
     "id": "353136da617542e1acd8f5b8945c9354",
     "source": "$text",
     "to_name": "text",
     "type": "labels",
     "value": {
      "start": 2451,
      "end": 2479,
      "labels": [
       "Email"
      ],
      "text": "manasvi.maheshwari@gmail.com"
     }
    },
    {
     "from_name": "ner",
     "honeypot": true,
     "id": "f72c25e0d8d44effbe57ac643ab53d80",
     "source": "$text",
     "to_name": "text",
     "type": "labels",
     "value": {
      "start": 2610,
      "end": 2619,
      "labels": [
       "GPE"
      ],
      "text": "New Delhi"
     }
    },
    {
     "from_name": "ner",
     "honeypot": true,
     "id": "971a8fdd16244935b60cc7b798e82ac9",
     "source": "$text",
     "to_name": "text",
     "type": "labels",
     "value": {
      "start": 2624,
      "end": 2630,
      "labels": [
       "PERSON"
      ],
      "text": "Kartik"
     }
    }
   ],
   "data": {
    "text": "KARTIK GOYAL kartikg479@gmail.com 9818865265 485A/3 Bhola Nath Nagar ,Shahdara Delhi-110032 Objective: \n Seeking a challenging and rewarding career where I can contribute my knowledge and skills for growth and development of Organization and be able to enhance my knowledge. \n Educational Qualifications: COURSE BOARD/UNIVERSITY SCHOOL/COLLEGE PERCENTAGE YEAR OF PASSING BJ(MC) IP UNIVERSITY \n Kasturi Ram College of Higher Education 78% 2015-2018 12th CBSE Bharat National Public \n 78% 2015 59% 2013 School 10th CBSE Dayanand Model Public School \n Professional Experience: Currently working in K.R MANGALAM UNIVERSITY, Sohna, Gurugram as a Lab Assistant since September 2018 Short Documentaries Film Video-graphy in College Events Photography in College Events \n One Month Internship in History Channel (10th July- 10th August 2017) \n Technical Skills Video-Editing software like FCP(Final Cut Pro), Adobe Premiere pro Photo-Editing software like Photoshop, Light room Audio-Editing software like Audacity. Worked on DSLR Camera like Canon 6d Mark II, Canon 5d Mark III, Canon 5d Mark IV, Canon 1DX, Sony A7 II, Sony A7R III, Gimbal like Ronin s, Zhiyun-Tech \n Crane 3, Teleprompter, Chroma setup. Freelancing Work Photography for Norway Embassy in Oberoi hotel, Delhi Marriage coverage like Traditional photography, Traditional Videography, Candid photography, Cinematography. Photography in Inter-College Festival \"EMINENCE\" Video-graphy in Music Video. E-commerce shoots of LED Screens. Promotional Events Corporate Photography Photography in web portal. \n Hobbies: Love to interact with people, photography, video-graphy, travel. Strengths: Self Motivated, I can adjust myself in any environment, I try my level best to work under all conditions. I am also good in handling team and work smoothly on deadlines. \n Personality traits: Hard working ,Positive, Team oriented Personal Information: Father s Name- Mr. Ravi kant Goyal Mother s Name- Mrs. Anita Goyal Date of Birth- 26 December 1996 Gender- Male Languages- English, Hindi Nationality- Indian Permanent address- 485A/3 Bhola Nath Nagar, Shahadara Delhi-110032 \n References Prof. (Dr.) Kiran Bala Dean, School of Journalism & Mass Communication K.R. Mangalam University, Sohna, Gurugram Ph. 9711909988 Email Id- kiranbkhanna75@gmail.com Dr. Manasvi Maheshwari Assistant Professor School of Journalism & Mass Communication K.R. Mangalam University, Sohna, Gurugram Ph. 9999311086 Email Id- manasvi.maheshwari@gmail.com \n Declaration: I hereby declare that above mentioned details are correct and complete to the best of my knowledge. \n Date: Place: New Delhi Mr. Kartik \n"
   },
   "task_path": "../tasks.json"
  }
 ]
}