{
 "completions": [
  {
   "id": 195,
   "lead_time": 20,
   "result": [
    {
     "from_name": "ner",
     "honeypot": true,
     "id": "4cc23ee605fd45ceb263a494a02c2be0",
     "source": "$text",
     "to_name": "text",
     "type": "labels",
     "value": {
      "start": 0,
      "end": 15,
      "labels": [
       "PERSON"
      ],
      "text": "Prateek Singhal"
     }
    },
    {
     "from_name": "ner",
     "honeypot": true,
     "id": "8e2fc3c8070945ada6e86f9d8ff5276c",
     "source": "$text",
     "to_name": "text",
     "type": "labels",
     "value": {
      "start": 94,
      "end": 107,
      "labels": [
       "GPE"
      ],
      "text": "Uttar Pradesh"
     }
    },
    {
     "from_name": "ner",
     "honeypot": true,
     "id": "be67b74e3e9d4bb3b7b5c428bde1b3c2",
     "source": "$text",
     "to_name": "text",
     "type": "labels",
     "value": {
      "start": 124,
      "end": 151,
      "labels": [
       "Email"
      ],
      "text": "prateeksinghal428@gmail.com"
     }
    },
    {
     "from_name": "ner",
     "honeypot": true,
     "id": "065ce4e260f74cc1a7162490e9a5365c",
     "source": "$text",
     "to_name": "text",
     "type": "labels",
     "value": {
      "start": 160,
      "end": 174,
      "labels": [
       "Phone"
      ],
      "text": "+91-8881886870"
     }
    },
    {
     "from_name": "ner",
     "honeypot": true,
     "id": "47e092ddbd32480eac03b45499dbfbd3",
     "source": "$text",
     "to_name": "text",
     "type": "labels",
     "value": {
      "start": 609,
      "end": 621,
      "labels": [
       "ORG"
      ],
      "text": "Smalsus Info"
     }
    },
    {
     "from_name": "ner",
     "honeypot": true,
     "id": "2e18f8c9ef91463983a3040f04a29dff",
     "source": "$text",
     "to_name": "text",
     "type": "labels",
     "value": {
      "start": 636,
      "end": 649,
      "labels": [
       "DATE"
      ],
      "text": "November 2018"
     }
    },
    {
     "from_name": "ner",
     "honeypot": true,
     "id": "bf6cf094a7d44847b9ec189fb22a8be7",
     "source": "$text",
     "to_name": "text",
     "type": "labels",
     "value": {
      "start": 672,
      "end": 690,
      "labels": [
       "Designation"
      ],
      "text": "Software Developer"
     }
    },
    {
     "from_name": "ner",
     "honeypot": true,
     "id": "5ddd7461dca248439d834f5e56fcff47",
     "source": "$text",
     "to_name": "text",
     "type": "labels",
     "value": {
      "start": 691,
      "end": 699,
      "labels": [
       "ORG"
      ],
      "text": "SHAREWEB"
     }
    },
    {
     "from_name": "ner",
     "honeypot": true,
     "id": "b598661d9eea4098b73ff73d0845f2e3",
     "source": "$text",
     "to_name": "text",
     "type": "labels",
     "value": {
      "start": 700,
      "end": 722,
      "labels": [
       "DATE"
      ],
      "text": "(January 2019 PRESENT)"
     }
    },
    {
     "from_name": "ner",
     "honeypot": true,
     "id": "7be06b2de7864aa78aa351442f15a7b3",
     "source": "$text",
     "to_name": "text",
     "type": "labels",
     "value": {
      "start": 1199,
      "end": 1224,
      "labels": [
       "DATE"
      ],
      "text": "November 2017-April 2018)"
     }
    },
    {
     "from_name": "ner",
     "honeypot": true,
     "id": "a0e8ebb656ee41c6b939a6b70ad121fa",
     "source": "$text",
     "to_name": "text",
     "type": "labels",
     "value": {
      "start": 1499,
      "end": 1508,
      "labels": [
       "DATE"
      ],
      "text": "July 2016"
     }
    },
    {
     "from_name": "ner",
     "honeypot": true,
     "id": "c77b6a5dc350482092876649d7854c89",
     "source": "$text",
     "to_name": "text",
     "type": "labels",
     "value": {
      "start": 1512,
      "end": 1551,
      "labels": [
       "ORG"
      ],
      "text": "Bharat Institute of Technology, Meerut."
     }
    },
    {
     "from_name": "ner",
     "honeypot": true,
     "id": "c7df62e6886d47dab41dc9dd37d04c6d",
     "source": "$text",
     "to_name": "text",
     "type": "labels",
     "value": {
      "start": 1707,
      "end": 1726,
      "labels": [
       "ORG"
      ],
      "text": "Indian Institute Of"
     }
    },
    {
     "from_name": "ner",
     "honeypot": true,
     "id": "3665f6bcc7624513870d54bb879d76ae",
     "source": "$text",
     "to_name": "text",
     "type": "labels",
     "value": {
      "start": 1749,
      "end": 1762,
      "labels": [
       "DATE"
      ],
      "text": "22nd Aug-18th"
     }
    },
    {
     "from_name": "ner",
     "honeypot": true,
     "id": "9ae43996abcc4e54b32f60ef7fd0db84",
     "source": "$text",
     "to_name": "text",
     "type": "labels",
     "value": {
      "start": 1765,
      "end": 1775,
      "labels": [
       "DATE"
      ],
      "text": "Nov, 2016."
     }
    },
    {
     "from_name": "ner",
     "honeypot": true,
     "id": "653d08b919f044e086416222b15ba507",
     "source": "$text",
     "to_name": "text",
     "type": "labels",
     "value": {
      "start": 1861,
      "end": 1884,
      "labels": [
       "DATE"
      ],
      "text": "18th Feb-14th Apr, 2016"
     }
    },
    {
     "from_name": "ner",
     "honeypot": true,
     "id": "fb7a9ea8b7124b789e79c4c431a315c2",
     "source": "$text",
     "to_name": "text",
     "type": "labels",
     "value": {
      "start": 648,
      "end": 649,
      "labels": [
       "ExperianceYears"
      ],
      "text": "8"
     }
    },
    {
     "from_name": "ner",
     "honeypot": true,
     "id": "80240eade674465eac9ef477a56dcbee",
     "source": "$text",
     "to_name": "text",
     "type": "labels",
     "value": {
      "start": 2094,
      "end": 2098,
      "labels": [
       "DATE"
      ],
      "text": "week"
     }
    },
    {
     "from_name": "ner",
     "honeypot": true,
     "id": "c1b837c710ca44c299b6961e8a446de2",
     "source": "$text",
     "to_name": "text",
     "type": "labels",
     "value": {
      "start": 2126,
      "end": 2141,
      "labels": [
       "DATE"
      ],
      "text": "27th July, 2017"
     }
    },
    {
     "from_name": "ner",
     "honeypot": true,
     "id": "c0bc3195f5d148feb0278d2407181e72",
     "source": "$text",
     "to_name": "text",
     "type": "labels",
     "value": {
      "start": 2145,
      "end": 2150,
      "labels": [
       "ORG"
      ],
      "text": "Kvch,"
     }
    },
    {
     "from_name": "ner",
     "honeypot": true,
     "id": "745eb5baa3f54d3cacd4789fc215a8cd",
     "source": "$text",
     "to_name": "text",
     "type": "labels",
     "value": {
      "start": 2151,
      "end": 2156,
      "labels": [
       "GPE"
      ],
      "text": "Noida"
     }
    },
    {
     "from_name": "ner",
     "honeypot": true,
     "id": "c15f1f7a88aa45d19ea07b89c67231e9",
     "source": "$text",
     "to_name": "text",
     "type": "labels",
     "value": {
      "start": 2424,
      "end": 2431,
      "labels": [
       "EducationDegree"
      ],
      "text": "B. Tech"
     }
    },
    {
     "from_name": "ner",
     "honeypot": true,
     "id": "7d4b46d75b7148adb5abf9407c3f23c2",
     "source": "$text",
     "to_name": "text",
     "type": "labels",
     "value": {
      "start": 2471,
      "end": 2507,
      "labels": [
       "ORG"
      ],
      "text": "APJ Abdul Kalam Technical University"
     }
    },
    {
     "from_name": "ner",
     "honeypot": true,
     "id": "7f404021c0c14927b32ca34c22c73f53",
     "source": "$text",
     "to_name": "text",
     "type": "labels",
     "value": {
      "start": 2508,
      "end": 2513,
      "labels": [
       "CARDINAL"
      ],
      "text": "63.4%"
     }
    },
    {
     "from_name": "ner",
     "honeypot": true,
     "id": "b0e8cedcb11140cf8fa74f5ff468b670",
     "source": "$text",
     "to_name": "text",
     "type": "labels",
     "value": {
      "start": 2514,
      "end": 2523,
      "labels": [
       "DATE"
      ],
      "text": "2014-2018"
     }
    },
    {
     "from_name": "ner",
     "honeypot": true,
     "id": "c2fe869dc5b7410e94e1f2b7b2cd9730",
     "source": "$text",
     "to_name": "text",
     "type": "labels",
     "value": {
      "start": 2552,
      "end": 2557,
      "labels": [
       "CARDINAL"
      ],
      "text": "79.2%"
     }
    }
   ],
   "data": {
    "text": "Prateek Singhal CONTACT INFORMATION F-1801,Supertech Livingston Crossing Republik ,Ghaziabad, Uttar Pradesh 201016 \n Email: prateeksinghal428@gmail.com Mobile: +91-8881886870 SUMMARY To gain an insight view in a challenging environment which provides me the opportunity to exercise my engineering and interpersonal skills that ensures enhancement of my knowledge and making a significant contribution in the success of the organization. \n TECHNICAL SKILLS Languages - Java , Angular JS , Bootstrap, HTML Database - MySQL Operating System - Windows Platform SharePoint \n WORK EXPERIENCE PROJECTS Organization: Smalsus Info Lab Duration: November 2018 -Present Designation: Software Developer SHAREWEB (January 2019 PRESENT) Description: Extending share point features using Angular JS to create share point pages which are working as single page application. Technology: HTML, CSS, JavaScript, Angular JS. Operating System: Windows 10 TCP SOP The credit pros search operating pages( March \n 2019-May2019) Description: Data managing through share point pages. Role: Completed solely Technology: Angular JS, Share point, HTML, CSS. Operating System: Windows 10 \n Data visualization Final year project( November 2017-April 2018) Description: Analyzing data and performing Demand forecasting for different regions. Technology: Big Data with Hadoop Operating System:Windows 10 \n SEMINAR AND WORKSHOPS ATTENDED ACHIEVEMENTS KEY SKILL PROFICIENCY EDUCATION Attended a seminar on Campus Commune conducted in July 2016 at Bharat Institute of Technology, Meerut. Succeeded in completing the online course on Basics of Remote Sensing ,Geographical Information System and Global Navigation Satellite System conducted by Indian Institute Of Remote Sensing during 22nd Aug-18th \n Nov, 2016. Attended a webinar on Basic 3-D Animation using Blender conducted by IIT Bombay from 18th Feb-14th Apr, 2016 through a Massive Open Online Course . Runner up in state level Robot War. Bagged 1st position in Robot war(zonal level) Earned a certificate of proficiency in Hadoop for having successfully completed the \n 8 week program with an A grade on 27th July, 2017 at Kvch, Noida \n Good command on programming in Angular JS. Possess the ability to adapt in any kind of situation. Quick learner, keen to learn and improve. Flexible and can work in a team. Strong leadership skills. \n Qualification/ Degree Board/University Percentage/ CGPA Year(s) B. Tech (Computer Science & Engineering) \n DR. APJ Abdul Kalam Technical University 63.4% 2014-2018 Intermediate School State \n 79.2% 2014 High School State 83.14% \n"
   },
   "task_path": "../tasks.json"
  }
 ]
}