{
 "completions": [
  {
   "id": 284,
   "lead_time": 20,
   "result": [
    {
     "from_name": "ner",
     "honeypot": true,
     "id": "5b562f59058b40789b951c201e5c9a2b",
     "source": "$text",
     "to_name": "text",
     "type": "labels",
     "value": {
      "start": 0,
      "end": 12,
      "labels": [
       "PERSON"
      ],
      "text": "Sohan Dhakad"
     }
    },
    {
     "from_name": "ner",
     "honeypot": true,
     "id": "f98ac0241b2847459a7b7bc16a60965c",
     "source": "$text",
     "to_name": "text",
     "type": "labels",
     "value": {
      "start": 13,
      "end": 37,
      "labels": [
       "GPE"
      ],
      "text": "Shivpuri, Madhya Pradesh"
     }
    },
    {
     "from_name": "ner",
     "honeypot": true,
     "id": "8d66c069018848c7a91fed3eeb2e22ce",
     "source": "$text",
     "to_name": "text",
     "type": "labels",
     "value": {
      "start": 272,
      "end": 289,
      "labels": [
       "Designation"
      ],
      "text": "ASSOCIATE TRAINEE"
     }
    },
    {
     "from_name": "ner",
     "honeypot": true,
     "id": "aa0351ff12c94e1288f578a260985c3f",
     "source": "$text",
     "to_name": "text",
     "type": "labels",
     "value": {
      "start": 293,
      "end": 300,
      "labels": [
       "ORG"
      ],
      "text": "INFOSYS"
     }
    },
    {
     "from_name": "ner",
     "honeypot": true,
     "id": "0a209aceba9f4900b2c25c339400c36f",
     "source": "$text",
     "to_name": "text",
     "type": "labels",
     "value": {
      "start": 323,
      "end": 339,
      "labels": [
       "GPE"
      ],
      "text": "Gurgaon, Haryana"
     }
    },
    {
     "from_name": "ner",
     "honeypot": true,
     "id": "b62394b07b0b43ffb07d00b43f8c7988",
     "source": "$text",
     "to_name": "text",
     "type": "labels",
     "value": {
      "start": 344,
      "end": 357,
      "labels": [
       "DATE"
      ],
      "text": "November 2016"
     }
    },
    {
     "from_name": "ner",
     "honeypot": true,
     "id": "7fb1afc7770b44ee97b876ce37bfbd60",
     "source": "$text",
     "to_name": "text",
     "type": "labels",
     "value": {
      "start": 361,
      "end": 368,
      "labels": [
       "DATE"
      ],
      "text": "Present"
     }
    },
    {
     "from_name": "ner",
     "honeypot": true,
     "id": "eb7283d277d7430daa50fa24d13113ba",
     "source": "$text",
     "to_name": "text",
     "type": "labels",
     "value": {
      "start": 791,
      "end": 808,
      "labels": [
       "ORG"
      ],
      "text": "Jiwaji University"
     }
    },
    {
     "from_name": "ner",
     "honeypot": true,
     "id": "0d3d797967f042bb8d6887f529f3328f",
     "source": "$text",
     "to_name": "text",
     "type": "labels",
     "value": {
      "start": 821,
      "end": 835,
      "labels": [
       "GPE"
      ],
      "text": "Madhya Pradesh"
     }
    },
    {
     "from_name": "ner",
     "honeypot": true,
     "id": "37c7f688a66946f69f3506155504a091",
     "source": "$text",
     "to_name": "text",
     "type": "labels",
     "value": {
      "start": 353,
      "end": 357,
      "labels": [
       "DATE"
      ],
      "text": "2016"
     }
    },
    {
     "from_name": "ner",
     "honeypot": true,
     "id": "28a46faab93746dbb0749cc1b8175acf",
     "source": "$text",
     "to_name": "text",
     "type": "labels",
     "value": {
      "start": 873,
      "end": 888,
      "labels": [
       "EducationDegree"
      ],
      "text": "cs profesional."
     }
    }
   ],
   "data": {
    "text": "Sohan Dhakad Shivpuri, Madhya Pradesh - Email me on Indeed: indeed.com/r/Sohan- Dhakad/038dfd47a0cf071f \n Serve the organization to apply my knowledge and skills to the best of my efforts in order to achieve organizational goals and continuous learning. \n WORK EXPERIENCE ASSOCIATE TRAINEE OF INFOSYS PROJECT OF GST PORTAL Gurgaon, Haryana - \n November 2016 to Present GURGAON. Monitoring the problems faced for the registration. Solving the problems of End User. Generating reports of escalations &amp; SLAs. Helping in issuance of Provisional IDs from GST. Ensuring the Quality checks &amp; control. Timely Delivery of resolutions for the End Users. Handling and proper knowledge of GST \n Documents. Ensuring SLA adherences and ensuring Companies Regulations &amp; Provisions. EDUCATION \n Jiwaji University - Shivpuri, Madhya Pradesh 2016 ADDITIONAL INFORMATION Parsuing cs profesional. \n https://www.indeed.com/r/Sohan-Dhakad/038dfd47a0cf071f isid=rex-download&ikw=download-top&co=IN https://www.indeed.com/r/Sohan-Dhakad/038dfd47a0cf071f \n"
   },
   "task_path": "../tasks.json"
  }
 ]
}