{
 "completions": [
  {
   "id": 1,
   "lead_time": 20,
   "result": [
    {
     "from_name": "ner",
     "honeypot": true,
     "id": "5d0693889135448490b3105529aebad5",
     "source": "$text",
     "to_name": "text",
     "type": "labels",
     "value": {
      "start": 0,
      "end": 12,
      "labels": [
       "PERSON"
      ],
      "text": "SURBHI TYAGI"
     }
    },
    {
     "from_name": "ner",
     "honeypot": true,
     "id": "7b9c755de21248609ad6146524571116",
     "source": "$text",
     "to_name": "text",
     "type": "labels",
     "value": {
      "start": 21,
      "end": 30,
      "labels": [
       "Phone"
      ],
      "text": "052846502"
     }
    },
    {
     "from_name": "ner",
     "honeypot": true,
     "id": "c75a7925a5cd433995dce52d0d9dc4c6",
     "source": "$text",
     "to_name": "text",
     "type": "labels",
     "value": {
      "start": 39,
      "end": 63,
      "labels": [
       "Email"
      ],
      "text": "surbhityagi760@gmail.com"
     }
    }
   ]
  }
 ]
}