{
 "completions": [
  {
   "id": 1,
   "lead_time": 20,
   "result": [
    {
     "from_name": "ner",
     "honeypot": true,
     "id": "0941034819fe4f02a3b5ebc8643f67fe",
     "source": "$text",
     "to_name": "text",
     "type": "labels",
     "value": {
      "start": 0,
      "end": 17,
      "labels": [
       "ORG"
      ],
      "text": "Kerala University"
     }
    },
    {
     "from_name": "ner",
     "honeypot": true,
     "id": "fb04fe61bbc34e5bb6b2e561e1e44094",
     "source": "$text",
     "to_name": "text",
     "type": "labels",
     "value": {
      "start": 18,
      "end": 22,
      "labels": [
       "DATE"
      ],
      "text": "2008"
     }
    }
   ]
  }
 ]
}