{
 "completions": [
  {
   "id": 1,
   "lead_time": 20,
   "result": [
    {
     "from_name": "ner",
     "honeypot": true,
     "id": "c78f6354f9e2494bbff09db6f4f196d9",
     "source": "$text",
     "to_name": "text",
     "type": "labels",
     "value": {
      "start": 0,
      "end": 15,
      "labels": [
       "PERSON"
      ],
      "text": "Ramesh chokkala"
     }
    },
    {
     "from_name": "ner",
     "honeypot": true,
     "id": "c0616d72d2cb49e0b2524d3e88d9fa14",
     "source": "$text",
     "to_name": "text",
     "type": "labels",
     "value": {
      "start": 16,
      "end": 25,
      "labels": [
       "GPE"
      ],
      "text": "Telangana"
     }
    }
   ]
  }
 ]
}