{
 "completions": [
  {
   "id": 1,
   "lead_time": 20,
   "result": [
    {
     "from_name": "ner",
     "honeypot": true,
     "id": "ca97b615a151405284335eaf65e30b36",
     "source": "$text",
     "to_name": "text",
     "type": "labels",
     "value": {
      "start": 47,
      "end": 54,
      "labels": [
       "EducationDegree"
      ],
      "text": "Diploma"
     }
    },
    {
     "from_name": "ner",
     "honeypot": true,
     "id": "17867908f2334f3c9390b82c15c0d2fc",
     "source": "$text",
     "to_name": "text",
     "type": "labels",
     "value": {
      "start": 79,
      "end": 124,
      "labels": [
       "ORG"
      ],
      "text": "SOFTECH INSTITUTE OF TECHNOLOGY AND MANAGMENT"
     }
    },
    {
     "from_name": "ner",
     "honeypot": true,
     "id": "83d61a0a3a3441ae93880196b92bef93",
     "source": "$text",
     "to_name": "text",
     "type": "labels",
     "value": {
      "start": 125,
      "end": 140,
      "labels": [
       "DATE"
      ],
      "text": "09/2017 07/2018"
     }
    }
   ]
  }
 ]
}