{
 "completions": [
  {
   "id": 190,
   "lead_time": 20,
   "result": [
    {
     "from_name": "ner",
     "honeypot": true,
     "id": "d5a15f1a9c314d3ea4afcc353d931fff",
     "source": "$text",
     "to_name": "text",
     "type": "labels",
     "value": {
      "start": 0,
      "end": 18,
      "labels": [
       "PERSON"
      ],
      "text": "Raja Chandra Mouli"
     }
    },
    {
     "from_name": "ner",
     "honeypot": true,
     "id": "bc9fe0abc8984536b8b16a9bcfbcedbb",
     "source": "$text",
     "to_name": "text",
     "type": "labels",
     "value": {
      "start": 19,
      "end": 43,
      "labels": [
       "GPE"
      ],
      "text": "Cuddapah, Andhra Pradesh"
     }
    },
    {
     "from_name": "ner",
     "honeypot": true,
     "id": "13eaec1c80db47649aa1b225489304ef",
     "source": "$text",
     "to_name": "text",
     "type": "labels",
     "value": {
      "start": 142,
      "end": 166,
      "labels": [
       "GPE"
      ],
      "text": "Cuddapah, Andhra Pradesh"
     }
    },
    {
     "from_name": "ner",
     "honeypot": true,
     "id": "ea796686c74d4f59babfa599a38eec2f",
     "source": "$text",
     "to_name": "text",
     "type": "labels",
     "value": {
      "start": 169,
      "end": 195,
      "labels": [
       "GPE"
      ],
      "text": "Vijayawada, Andhra Pradesh"
     }
    },
    {
     "from_name": "ner",
     "honeypot": true,
     "id": "4acff133ef49482f81256c6a242a6ff1",
     "source": "$text",
     "to_name": "text",
     "type": "labels",
     "value": {
      "start": 198,
      "end": 227,
      "labels": [
       "GPE"
      ],
      "text": "Visakhapatnam, Andhra Pradesh"
     }
    },
    {
     "from_name": "ner",
     "honeypot": true,
     "id": "9d4ba9b2b6874d73a4a195d0ea941b9c",
     "source": "$text",
     "to_name": "text",
     "type": "labels",
     "value": {
      "start": 142,
      "end": 166,
      "labels": [
       "GPE"
      ],
      "text": "Cuddapah, Andhra Pradesh"
     }
    },
    {
     "from_name": "ner",
     "honeypot": true,
     "id": "7f28cf06614243bc914707b1b451ee62",
     "source": "$text",
     "to_name": "text",
     "type": "labels",
     "value": {
      "start": 295,
      "end": 303,
      "labels": [
       "DATE"
      ],
      "text": "May 2018"
     }
    },
    {
     "from_name": "ner",
     "honeypot": true,
     "id": "a5db1c5a18374df781be0fefc55900c4",
     "source": "$text",
     "to_name": "text",
     "type": "labels",
     "value": {
      "start": 307,
      "end": 314,
      "labels": [
       "DATE"
      ],
      "text": "Present"
     }
    },
    {
     "from_name": "ner",
     "honeypot": true,
     "id": "42596bfa19ae440a85bb5903633d893c",
     "source": "$text",
     "to_name": "text",
     "type": "labels",
     "value": {
      "start": 327,
      "end": 335,
      "labels": [
       "EducationDegree"
      ],
      "text": "BSc,Mecs"
     }
    },
    {
     "from_name": "ner",
     "honeypot": true,
     "id": "d43a74d5a36c46f68b17209c56cd4f48",
     "source": "$text",
     "to_name": "text",
     "type": "labels",
     "value": {
      "start": 375,
      "end": 394,
      "labels": [
       "ORG"
      ],
      "text": "ards collage kadapa"
     }
    },
    {
     "from_name": "ner",
     "honeypot": true,
     "id": "1e16181154804c2bbd53ec4c46cfb40f",
     "source": "$text",
     "to_name": "text",
     "type": "labels",
     "value": {
      "start": 268,
      "end": 292,
      "labels": [
       "GPE"
      ],
      "text": "Cuddapah, Andhra Pradesh"
     }
    },
    {
     "from_name": "ner",
     "honeypot": true,
     "id": "6352d77cae534e0eafc3019c229bf7bd",
     "source": "$text",
     "to_name": "text",
     "type": "labels",
     "value": {
      "start": 295,
      "end": 303,
      "labels": [
       "DATE"
      ],
      "text": "May 2018"
     }
    },
    {
     "from_name": "ner",
     "honeypot": true,
     "id": "4528fe2817ff48489ac9c76a8fa69e9b",
     "source": "$text",
     "to_name": "text",
     "type": "labels",
     "value": {
      "start": 436,
      "end": 445,
      "labels": [
       "DATE"
      ],
      "text": "June 2019"
     }
    },
    {
     "from_name": "ner",
     "honeypot": true,
     "id": "b197f1c758744d31b3affe7ff6ecc3bf",
     "source": "$text",
     "to_name": "text",
     "type": "labels",
     "value": {
      "start": 480,
      "end": 496,
      "labels": [
       "ExperianceYears"
      ],
      "text": "ess than 1 year)"
     }
    },
    {
     "from_name": "ner",
     "honeypot": true,
     "id": "0b9599ea013345f8b52d2267dd65eb79",
     "source": "$text",
     "to_name": "text",
     "type": "labels",
     "value": {
      "start": 544,
      "end": 557,
      "labels": [
       "DATE"
      ],
      "text": "year May 2018"
     }
    },
    {
     "from_name": "ner",
     "honeypot": true,
     "id": "e5d38330385b414b8f585c5ebd79b2e7",
     "source": "$text",
     "to_name": "text",
     "type": "labels",
     "value": {
      "start": 307,
      "end": 314,
      "labels": [
       "DATE"
      ],
      "text": "Present"
     }
    }
   ],
   "data": {
    "text": "Raja Chandra Mouli Cuddapah, Andhra Pradesh - Email me on Indeed: indeed.com/r/Raja-Chandra- Mouli/445cbf3eb0a361cd \n Willing to relocate to: Cuddapah, Andhra Pradesh - Vijayawada, Andhra Pradesh - Visakhapatnam, Andhra Pradesh \n WORK EXPERIENCE ms office Microsoft - Cuddapah, Andhra Pradesh - May 2018 to Present \n EDUCATION BSc,Mecs 2nd year completed in Computer science ards collage kadapa - Cuddapah, Andhra Pradesh \n May 2018 to June 2019 SKILLS ms office, internet,java ( ess than 1 year) \n CERTIFICATIONS/LICENSES Degree,BSc(MECs) 2nd year May 2018 to Present ADDITIONAL INFORMATION 3-101 KC Narayana Street,new madavaram(v),Vontimitta(M),Kadapa(D) \n https://www.indeed.com/r/Raja-Chandra-Mouli/445cbf3eb0a361cd isid=rex-download&ikw=download-top&co=IN https://www.indeed.com/r/Raja-Chandra-Mouli/445cbf3eb0a361cd \n"
   },
   "task_path": "../tasks.json"
  }
 ]
}