{
 "completions": [
  {
   "id": 1,
   "lead_time": 20,
   "result": [
    {
     "from_name": "ner",
     "honeypot": true,
     "id": "4cf290a0053348298bb567084fdb79b1",
     "source": "$text",
     "to_name": "text",
     "type": "labels",
     "value": {
      "start": 33,
      "end": 39,
      "labels": [
       "EducationDegree"
      ],
      "text": "B.Tech"
     }
    },
    {
     "from_name": "ner",
     "honeypot": true,
     "id": "de024b40d27c402581b7e51da78300a1",
     "source": "$text",
     "to_name": "text",
     "type": "labels",
     "value": {
      "start": 75,
      "end": 149,
      "labels": [
       "ORG"
      ],
      "text": "School Roland Institute of Technology, Berhampur, Odisha. Mahamayee Mahila"
     }
    },
    {
     "from_name": "ner",
     "honeypot": true,
     "id": "f71fd44503b04b328423114e0758aa59",
     "source": "$text",
     "to_name": "text",
     "type": "labels",
     "value": {
      "start": 114,
      "end": 131,
      "labels": [
       "GPE"
      ],
      "text": "Berhampur, Odisha"
     }
    }
   ]
  }
 ]
}