{
 "completions": [
  {
   "id": 1,
   "lead_time": 20,
   "result": [
    {
     "from_name": "ner",
     "honeypot": true,
     "id": "5b9abd8036ca4a22bffe5be08527169b",
     "source": "$text",
     "to_name": "text",
     "type": "labels",
     "value": {
      "start": 12,
      "end": 19,
      "labels": [
       "Designation"
      ],
      "text": "analyst"
     }
    },
    {
     "from_name": "ner",
     "honeypot": true,
     "id": "0377f37805c04ebeaaa014b51a752641",
     "source": "$text",
     "to_name": "text",
     "type": "labels",
     "value": {
      "start": 23,
      "end": 38,
      "labels": [
       "ORG"
      ],
      "text": "Teleperformance"
     }
    },
    {
     "from_name": "ner",
     "honeypot": true,
     "id": "6ed278d76f0045b3994cfec4b3f5620e",
     "source": "$text",
     "to_name": "text",
     "type": "labels",
     "value": {
      "start": 39,
      "end": 47,
      "labels": [
       "GPE"
      ],
      "text": "Gurugram"
     }
    },
    {
     "from_name": "ner",
     "honeypot": true,
     "id": "811b81e0370144fda07624acca78d1c2",
     "source": "$text",
     "to_name": "text",
     "type": "labels",
     "value": {
      "start": 53,
      "end": 77,
      "labels": [
       "DATE"
      ],
      "text": "July 2018 to march 2019."
     }
    }
   ]
  }
 ]
}