{
 "completions": [
  {
   "id": 1,
   "lead_time": 20,
   "result": [
    {
     "from_name": "ner",
     "honeypot": true,
     "id": "73ba873f2bc94e9ebabc64884bd9a538",
     "source": "$text",
     "to_name": "text",
     "type": "labels",
     "value": {
      "start": 11,
      "end": 18,
      "labels": [
       "ORG"
      ],
      "text": "Infosys"
     }
    },
    {
     "from_name": "ner",
     "honeypot": true,
     "id": "0cf727fb9604427fa375dbd7fb2dd4e4",
     "source": "$text",
     "to_name": "text",
     "type": "labels",
     "value": {
      "start": 24,
      "end": 45,
      "labels": [
       "Designation"
      ],
      "text": "developer and support"
     }
    },
    {
     "from_name": "ner",
     "honeypot": true,
     "id": "4319cdfab8e54552bc565476abee1b7f",
     "source": "$text",
     "to_name": "text",
     "type": "labels",
     "value": {
      "start": 56,
      "end": 64,
      "labels": [
       "DATE"
      ],
      "text": "May 2015"
     }
    },
    {
     "from_name": "ner",
     "honeypot": true,
     "id": "1a4cf64385e542b2a153f7a2a91b7511",
     "source": "$text",
     "to_name": "text",
     "type": "labels",
     "value": {
      "start": 68,
      "end": 75,
      "labels": [
       "DATE"
      ],
      "text": "Present"
     }
    }
   ]
  }
 ]
}