{
 "completions": [
  {
   "id": 1,
   "lead_time": 20,
   "result": [
    {
     "from_name": "ner",
     "honeypot": true,
     "id": "41cb7bc6361f454d8af8c4ea5e316643",
     "source": "$text",
     "to_name": "text",
     "type": "labels",
     "value": {
      "start": 33,
      "end": 63,
      "labels": [
       "ORG"
      ],
      "text": "Morgan (I) Pvt. Ltd, New Delhi"
     }
    },
    {
     "from_name": "ner",
     "honeypot": true,
     "id": "fc26299d9c804a0894faf85d38ba4b2e",
     "source": "$text",
     "to_name": "text",
     "type": "labels",
     "value": {
      "start": 79,
      "end": 100,
      "labels": [
       "DATE"
      ],
      "text": "Jan-2014 to June-2014"
     }
    },
    {
     "from_name": "ner",
     "honeypot": true,
     "id": "dd3fb08b174d4f27a1a5281b10c9eb06",
     "source": "$text",
     "to_name": "text",
     "type": "labels",
     "value": {
      "start": 115,
      "end": 141,
      "labels": [
       "Designation"
      ],
      "text": "Customer Support Engineer."
     }
    }
   ]
  }
 ]
}