{
 "completions": [
  {
   "id": 1,
   "lead_time": 20,
   "result": [
    {
     "from_name": "ner",
     "honeypot": true,
     "id": "bcc653f9da874ef6b118f14f1871c18a",
     "source": "$text",
     "to_name": "text",
     "type": "labels",
     "value": {
      "start": 42,
      "end": 113,
      "labels": [
       "ORG"
      ],
      "text": "YMCA University of Science & Technology Faridabad DAV Centenary College"
     }
    },
    {
     "from_name": "ner",
     "honeypot": true,
     "id": "e28029dbb9b742d89921fc2c36376436",
     "source": "$text",
     "to_name": "text",
     "type": "labels",
     "value": {
      "start": 82,
      "end": 91,
      "labels": [
       "GPE"
      ],
      "text": "Faridabad"
     }
    }
   ]
  }
 ]
}