{
 "completions": [
  {
   "id": 1,
   "lead_time": 20,
   "result": [
    {
     "from_name": "ner",
     "honeypot": true,
     "id": "dde21a7ac4114a60a309a979145f7bd1",
     "source": "$text",
     "to_name": "text",
     "type": "labels",
     "value": {
      "start": 62,
      "end": 69,
      "labels": [
       "ExperianceYears"
      ],
      "text": "6 month"
     }
    },
    {
     "from_name": "ner",
     "honeypot": true,
     "id": "5cdd36235d8e4d20a310188f9e4d9df8",
     "source": "$text",
     "to_name": "text",
     "type": "labels",
     "value": {
      "start": 134,
      "end": 154,
      "labels": [
       "Skills"
      ],
      "text": "HTML, CSS, Wordpress"
     }
    }
   ]
  }
 ]
}